LICENSE
MANIFEST.in
README.md
package.json
setup.py
survival_curve/SurvivalCurve.py
survival_curve/__init__.py
survival_curve/_imports_.py
survival_curve/metadata.json
survival_curve/package-info.json
survival_curve/survival_curve.min.js
survival_curve/survival_curve.min.js.map
survival_curve/survival_stats.py
survival_curve.egg-info/PKG-INFO
survival_curve.egg-info/SOURCES.txt
survival_curve.egg-info/dependency_links.txt
survival_curve.egg-info/top_level.txt