Metadata-Version: 2.1
Name: survival-curve
Version: 0.0.6
Summary: Reusable React-based UI for Dash apps that computes and plots a Kaplan-Meier curve entirely using raw event and time-to-event data passed from Dash app. It eliminatevival analysis libraries, making it lightweight and frontend-driven.
Home-page: UNKNOWN
Author: Xavier Llobet <llbt.nvs.x@gmail.com>
License: MIT
Platform: UNKNOWN
Classifier: Framework :: Dash
License-File: LICENSE
